google_env/__init__.py
google_env-0.4.0.data/scripts/google_env
google_env-0.4.0.dist-info/METADATA
google_env-0.4.0.dist-info/WHEEL
google_env-0.4.0.dist-info/top_level.txt
google_env-0.4.0.dist-info/RECORD
